[{"name":"Hernán Torres","screen_name":"HERNANTORRES250"},{"name":"Francisco","screen_name":"sanjofra46"},{"name":"Alice Llorens","screen_name":"AliceLlorens"},{"name":"nacho vidoret","screen_name":"ividovt"},{"name":"GAP","screen_name":"infogaparg"},{"name":"Ines","screen_name":"Michell32428884"},{"name":"Jack Arellano","screen_name":"Jack_aar"},{"name":"Proyetech","screen_name":"proyetech"},{"name":"Ricardo Cornejo","screen_name":"RicardoCornejoV"},{"name":"ArtClickeando","screen_name":"artclickeando"},{"name":"Daniel Machado","screen_name":"danmach4"},{"name":"HJNC","screen_name":"hernanjnc"},{"name":"Alberto Uribe","screen_name":"Piping_Oil_Gas"},{"name":"FreeToursCusco-FTF","screen_name":"FreeToursCusco"},{"name":"Diana Maria Silva","screen_name":"Diana_1010"},{"name":"Mariana Ines Thoss","screen_name":"MarianaThoss"},{"name":"Alquileres Videobeam","screen_name":"AlquileresVideo"},{"name":"prosperidad total","screen_name":"rightprosperity"},{"name":"ABLOY Colombia S.A.S","screen_name":"AbloyColombia"},{"name":"Joka","screen_name":"mjokabeth1"},{"name":"jose","screen_name":"josearca7766"},{"name":"Nelson David","screen_name":"nfleitas2013"},{"name":"H.Boccacci AmericaRH","screen_name":"AmericaRH"},{"name":"Jhonny D.","screen_name":"ElJhonnyDavid"},{"name":"Eze","screen_name":"gereze_"},{"name":"Gary Pacheco","screen_name":"Pache9205"},{"name":"Astrid Arroyave Art","screen_name":"ArroyaveArte"},{"name":"Analía Bustamante","screen_name":"analia_vb"},{"name":"Katrin Boeke-Purkis","screen_name":"BoekeKatrin"},{"name":"Marco Antonio Gomez","screen_name":"marco2912"},{"name":"María Carla Oller","screen_name":"mcarlaoller"},{"name":"Claudio chaverri bar","screen_name":"ChaverriBar"},{"name":"AS Recursos Humanos","screen_name":"asrrhh"},{"name":"Orlando Bastardo","screen_name":"Ojbastardo"},{"name":"Jorge Gonzalez Rodri","screen_name":"ColRodri"},{"name":"Jose Maria Perez","screen_name":"jmariaperezg"},{"name":"Cognos NewsBot","screen_name":"Cognos_NewsBot"},{"name":"Alexis Cabarcas","screen_name":"CabarcasAlexis"},{"name":"Laura G.Guillén","screen_name":"lgisellegr"},{"name":"PlanetaEmpleos","screen_name":"PlanetaEmpleos"},{"name":"Christian R ♛","screen_name":"Chrisfelip"},{"name":"Steven Leung","screen_name":"StevenLeung7"},{"name":"Juan Reyes","screen_name":"Juanreyes887"},{"name":"matheo","screen_name":"matheodoros12"},{"name":"Dani","screen_name":"danielitahdez1"},{"name":"Roger Coreeea","screen_name":"CorreaRge"},{"name":"Vicky Cruz","screen_name":"VictoriaCruz999"},{"name":"Melissa Ortiz","screen_name":"Meli23Ot"},{"name":"superate arte","screen_name":"comovastu"},{"name":"Jorge Blandon","screen_name":"JorgeBlnd"},{"name":"Isabella Roldan","screen_name":"Isarold4n73"},{"name":"Don pastor","screen_name":"pastor2035"},{"name":"Valentina","screen_name":"ValenTREXG"},{"name":"Rosario Jaramillo","screen_name":"Rosario_Jara2e"},{"name":"John Q.","screen_name":"quicenosjhon"},{"name":"Nata Ramírez","screen_name":"NatyRamire"},{"name":"Sarita Velez","screen_name":"saritavelez_w"},{"name":"Juan Diego B.","screen_name":"JuanDiegoBog"},{"name":"ecologistics","screen_name":"Recojaesascosas"},{"name":"Alberto Arango","screen_name":"AlbertArang"},{"name":"Juliana Castrillon","screen_name":"July_castri"},{"name":"Dominique Love","screen_name":"Dominique6776"},{"name":"Édgar Morales","screen_name":"Edgar_877"},{"name":"Fanny .","screen_name":"fany2323jean"},{"name":"Ekaterina Sofía","screen_name":"ekaterinasofiam"},{"name":"Dark Side","screen_name":"Dark_S7de"},{"name":"CaroBarona","screen_name":"CaroBarona"},{"name":"Alberto Tupaz","screen_name":"Albertupaz"},{"name":"Cuadros que Hablan","screen_name":"CuadrosqHablan"},{"name":"Andrei","screen_name":"CAOP11"},{"name":"Vicky Chimento","screen_name":"VickyChimento"},{"name":"Darwin","screen_name":"PJavda"},{"name":"Silvia Fernandes","screen_name":"fernandesilvia"},{"name":"Horacio Brescia","screen_name":"bresciahoracio"},{"name":"Julia Perez","screen_name":"Puki2727"},{"name":"Pymesconectadasempl","screen_name":"pymesconecempl"},{"name":"rapunzel","screen_name":"rapunzel1054"},{"name":"Pam","screen_name":"PamInABlueBox"},{"name":"Lu Deluca","screen_name":"ludelucaa"},{"name":"Juli Gees","screen_name":"JuliGees"},{"name":"Open Max","screen_name":"OPENMAXweb"},{"name":"Nicolas Garcia","screen_name":"Nicogarcia28120"},{"name":"Ale Pintos","screen_name":"alexapintos"},{"name":"Noticias de RRHH","screen_name":"RRHH_LATAM"},{"name":"pintor industrial","screen_name":"EddyCarrasca"},{"name":"DC","screen_name":"DonChevo"},{"name":"Paco Acosta","screen_name":"AcostaPaco"},{"name":"Jaime Crazy Peru","screen_name":"JaimeCrazyPeru"},{"name":"Publica Pmi RSur","screen_name":"Publi_PMI_Rsur"},{"name":"@cpulido","screen_name":"KmPulido"},{"name":"Ricardo Díaz Araux","screen_name":"ricardoda75"},{"name":"Nathalia Lascano","screen_name":"nathalialascano"},{"name":"alexis maureira","screen_name":"neshi37"},{"name":"dashekagrove","screen_name":"DashekaGrove"},{"name":"skore30","screen_name":"nestoraponte2"},{"name":"Ale Beristain","screen_name":"beristain_ale"},{"name":"Federico Hernández","screen_name":"Fede_elCuco"},{"name":"Maria Daniela","screen_name":"mariadanielaag"},{"name":"Ing. Victor Vergara ","screen_name":"ingvvergara"},{"name":"jorgesanchezjasa","screen_name":"05fe4dc10d554f9"},{"name":"Pariwana Hostels","screen_name":"PariwanaHostels"},{"name":"Oscar Jose","screen_name":"ojmarco"},{"name":"Juan Carlos Pelayo","screen_name":"kakopelayo"},{"name":"Maria Matamoros","screen_name":"pasteleriapicc1"},{"name":"Yess","screen_name":"yess_ita"},{"name":"karen citlalli","screen_name":"karen_citlalli"},{"name":"ricardo ayala","screen_name":"Riickardok"},{"name":"MARKET PRODUCCIONES","screen_name":"marketProduccio"},{"name":"a","screen_name":"AkuraToluca"},{"name":"Colombia Agent","screen_name":"Colombia_Agent"},{"name":"Christian Anthony","screen_name":"LiianDench"},{"name":"Developers Board Co","screen_name":"devboardco"},{"name":"Capital Empleo","screen_name":"CapitalEmpleo"},{"name":"ALG Talent Solutions","screen_name":"AlgTalent"},{"name":"Luis Ernesto Acosta","screen_name":"luise2405"},{"name":"Generador de Empleo","screen_name":"GeneradorEmpleo"},{"name":"Mohamad Jamhour","screen_name":"6d352379ec3249c"},{"name":"Diego","screen_name":"dieru25"},{"name":"natalia barajas","screen_name":"nataliabarajas2"},{"name":"HeadHunter Monterrey","screen_name":"headhunterMty"},{"name":"MauricioGiraldoZ","screen_name":"dmgiraldoz"},{"name":"Johan Ramirez","screen_name":"johanramirez72"},{"name":"luis angel perez gar","screen_name":"luis19859"},{"name":"John Alexander","screen_name":"Johnrey1015"},{"name":"Marcelo Bacca","screen_name":"marcelo_bacca"},{"name":"Mencha1975","screen_name":"mencha1975"},{"name":"Alejandro Iriarte c.","screen_name":"alejodj50"},{"name":"Franco Ardila","screen_name":"FrancoArdila"},{"name":"EL MEJICANO","screen_name":"1951Jmrv"},{"name":"Mimi Gonzalez","screen_name":"mimi_ta2"},{"name":"Erick Cabrera ","screen_name":"erickconck"},{"name":"Stephanie Rivero","screen_name":"Steprio"},{"name":"GIOVANNY GALINDO","screen_name":"iovannygalindo"},{"name":".","screen_name":"alejo7419"},{"name":"Diego  Lobartolo","screen_name":"Diego_Lobartolo"},{"name":"leonardo valles","screen_name":"leonardovalles"},{"name":"MauMarg","screen_name":"MauMarg"},{"name":"fabian chaverra","screen_name":"fchaverra82"},{"name":"Diana Hernández","screen_name":"DianaProcesos"},{"name":"Aura Gutierrez","screen_name":"AuriGutierrez1"},{"name":"Gilda Vega Charris","screen_name":"g_vegach"},{"name":"diego obregon","screen_name":"diegaoo88"},{"name":"Valeria Uzcategui","screen_name":"valeflower17"},{"name":"Jason Cruz","screen_name":"jasoncruz85"},{"name":"Eduardo Daw","screen_name":"eduardo_daw"},{"name":"Carlos Henao","screen_name":"chenaoqu"},{"name":"Douglas Perez","screen_name":"dovape56"},{"name":"parra tique","screen_name":"DonnyTique"},{"name":" Fabian Alvarez","screen_name":"faro_067"},{"name":"Orlando Blanco","screen_name":"oblanco23"},{"name":"DANNY SALVADOR","screen_name":"dannyrauls"},{"name":"mixter gustavo","screen_name":"gustavomosquer1"},{"name":"Alberto Isusi","screen_name":"AlbertoIsusi"},{"name":"Natalia Salazar  A","screen_name":"natasala"},{"name":"Antonio","screen_name":"ajjbv65"},{"name":"Coriman12","screen_name":"Coriman12"},{"name":"Eiber Eloy Azuaje","screen_name":"EiberEloy"},{"name":"Rokyy51","screen_name":"rokyy51"},{"name":"Activanet","screen_name":"Activanet2"},{"name":"alfredo estrada nava","screen_name":"estradan63"},{"name":"Jorge A. Ardila","screen_name":"ArdilaJorge_AJ"},{"name":"Ctzen","screen_name":"ctzenco"},{"name":"orlando rey","screen_name":"oreyarca"},{"name":"JAVIER CAICEDO","screen_name":"JAVIERJacg102"},{"name":"FCSosa","screen_name":"fcsosa"},{"name":"Prevención es Acción","screen_name":"esprevencion"},{"name":"Juan Carlos Barceló","screen_name":"juancbarcelo"},{"name":"Yirleidys","screen_name":"Yirjota"},{"name":"Andres Molina","screen_name":"andresmol"},{"name":"Soy_ChrisTo","screen_name":"LamaT84"},{"name":"Juan Carlos Baron","screen_name":"JCarlosBaron"},{"name":"Danaee Arevalo","screen_name":"DDanaee"},{"name":"eBusinessPeru","screen_name":"eBusinessPeru"},{"name":"John Álvarez","screen_name":"jhonalvarez1"},{"name":"carmen soledad perez","screen_name":"carmenso99"},{"name":"Gabita","screen_name":"gavisu49"},{"name":"Freddy Ruiz","screen_name":"FreRuiz2010"},{"name":"Patricia Imbett","screen_name":"Pimbettt"},{"name":"Diana Riascos","screen_name":"DianaRiascos"},{"name":"gabdesideri","screen_name":"gabriel_desi"},{"name":"gabo CarCar","screen_name":"gabocarcar"},{"name":"CARLO$ MORA","screen_name":"MORINGAS"},{"name":"Ender Velazco","screen_name":"endervelazco"},{"name":"Luis Cesar Nuñez","screen_name":"mecorit"},{"name":"Carol E.","screen_name":"Cpep_342"},{"name":"Isabel Andrade Alcaz","screen_name":"Isabel_Alcazar"},{"name":"HEINER JANSEN","screen_name":"HJANCA"},{"name":"Hardik Pravin Pathak","screen_name":"GorgeousHardik"},{"name":"karen aviles","screen_name":"miyuki_inukai"},{"name":"Dany ","screen_name":"danylopm"},{"name":"RALPHDJ1","screen_name":"RAFAELDJ1"},{"name":"juan torres","screen_name":"saryhtorres"},{"name":"Irene Manrique","screen_name":"irenemng"},{"name":"QuieroUnEntrenador","screen_name":"quierounentreno"},{"name":"EstructuraSostenible","screen_name":"A1Estructuras"},{"name":"Victor H Garcia M","screen_name":"victorhugogar32"},{"name":"Martho Jiménez","screen_name":"DuMbLeDoRe17"},{"name":"Eduardo CHANEL","screen_name":"CHANEL_ART5"},{"name":"Anderson","screen_name":"Stev_andy"},{"name":"edwin soto","screen_name":"Soto1915"},{"name":"Gino Ipanaque","screen_name":"ginopepino01"},{"name":"Bcamacho","screen_name":"bcamachito"},{"name":"NINI JOHANA","screen_name":"NINIJOHANA18"},{"name":"Jean P. Bracho","screen_name":"JeanpaulB"},{"name":"Eduardo Alcerreca","screen_name":"ealcerreca"},{"name":"Karla Morales P","screen_name":"Karshlee"},{"name":"Juan Pablo Rojas","screen_name":"juanpablorojasl"},{"name":"#Jan_Herzog_2018 !","screen_name":"Jan_Herzog"},{"name":"Adolfo Guzman","screen_name":"guzman_adolfo"},{"name":"Tzeitel Topel","screen_name":"6tel"},{"name":"Federico Gomez G","screen_name":"fedegomez"},{"name":"KAT","screen_name":"Katherucita"},{"name":"lucas giraldo","screen_name":"sacul031208"},{"name":"Cahterina","screen_name":"rcahterina"},{"name":"Forums Consulting","screen_name":"ForumsCoach"},{"name":"Edwin Laydera","screen_name":"elaydera"},{"name":"Daniel GA","screen_name":"danjoguevara"},{"name":"Francisco Diaz","screen_name":"frandiaz1"},{"name":"Sil","screen_name":"Silmendez1980"},{"name":"Skeyla Márquez","screen_name":"skeylam"},{"name":"Jorge Prieto","screen_name":"jorkao"},{"name":"Despegar Argentina","screen_name":"DespegarAr"},{"name":"Despegar.com","screen_name":"Despegar"},{"name":"FeRn4nDo ViLlaMiZaR","screen_name":"FeVillamizar"},{"name":"MJ","screen_name":"MJ__Garcia"},{"name":"joclopz","screen_name":"Joclopz"},{"name":"Dayana Mavarez","screen_name":"Dayana_mavarez"},{"name":"Ricardo Roa","screen_name":"rikardroa"},{"name":"Gote","screen_name":"gote11"},{"name":"Nacary","screen_name":"nacaryg"},{"name":"Paola Meza Maldonado","screen_name":"CMpaolameza"},{"name":"Carlos Henao","screen_name":"cahenaoh"},{"name":"YRIALBER","screen_name":"YRIPEREIR"},{"name":"DANIEL PRIETO","screen_name":"prietod2"},{"name":"Alfredo Yedra","screen_name":"AlfredoJY"},{"name":"carloscaro","screen_name":"karlozkaro"},{"name":"El Ingeniero Civil","screen_name":"Ing_Civil1"},{"name":"Rosemarie  Bruhl","screen_name":"rosemariebruhl"},{"name":"NESTOR BARON","screen_name":"Nestorbaron"},{"name":"Leonidas Uzcategui","screen_name":"leouzcategui"},{"name":"Laura Roncallo","screen_name":"lrlafontt"},{"name":"Christian Mendoza L.","screen_name":"chadmelu"},{"name":"Yubeilis.","screen_name":"Yubeilis"},{"name":"Empléate","screen_name":"empleate"},{"name":"Erika Méndez","screen_name":"ingerikamendez"},{"name":"Juan","screen_name":"vergaraj"},{"name":"Nelson Yaya","screen_name":"feisbukpages"},{"name":"Lourdes Mujica Gómez","screen_name":"LouMujica"},{"name":"Oscar David","screen_name":"ososorio"}]